nlpia/__init__.py
nlpia/anki.py
nlpia/book_parser.py
nlpia/clean_alice.py
nlpia/constants.py
nlpia/data_utils.py
nlpia/embedders.py
nlpia/features.py
nlpia/futil.py
nlpia/gensim_utils.py
nlpia/geo.py
nlpia/google_drive.py
nlpia/google_trends.py
nlpia/highd.py
nlpia/loaders.py
nlpia/mavis_greetings.py
nlpia/models.py
nlpia/plots.py
nlpia/regexes.py
nlpia/settings.py
nlpia/skeleton.py
nlpia/talk.py
nlpia/transcoders.py
nlpia/translate.py
nlpia/translators.py
nlpia/utils.py
nlpia/w2v_utils.py
nlpia/web.py
nlpia/word_sentiment.py
nlpia/bigdata/glove_test.txt
nlpia/book/__init__.py
nlpia/book/data/data_stats.pkl
nlpia/book/data/decoder_seq2seq.hd5
nlpia/book/data/dialog.txt
nlpia/book/data/encoder_seq2seq.hd5
nlpia/book/data/mavis-batey-greetings.txt
nlpia/book/data/mavis-batey-sentences.txt
nlpia/book/data/programming languages.txt
nlpia/book/examples/__init__.py
nlpia/book/examples/brownlee_seq2seq.py
nlpia/book/examples/brownlee_seq2seq_3.py
nlpia/book/examples/ch02.md
nlpia/book/examples/ch02.py
nlpia/book/examples/ch02_sentiment.py
nlpia/book/examples/ch03-2.py
nlpia/book/examples/ch03.md
nlpia/book/examples/ch03.py
nlpia/book/examples/ch03.rst
nlpia/book/examples/ch03_2.ipynb
nlpia/book/examples/ch03_bm25.py
nlpia/book/examples/ch03_zipf.py
nlpia/book/examples/ch04.py
nlpia/book/examples/ch04.rst
nlpia/book/examples/ch04.svdfail.py
nlpia/book/examples/ch04.svdfail.rst
nlpia/book/examples/ch04_catdog_lsa.rst
nlpia/book/examples/ch04_catdog_lsa_3x6x16.py
nlpia/book/examples/ch04_catdog_lsa_4x8x200.py
nlpia/book/examples/ch04_catdog_lsa_9x4x12.py
nlpia/book/examples/ch04_catdog_lsa_sorted.py
nlpia/book/examples/ch04_horse.py
nlpia/book/examples/ch04_ldia_comparison.py
nlpia/book/examples/ch04_sklearn_pca_source.py
nlpia/book/examples/ch04_spam_lda.py
nlpia/book/examples/ch04_stanford_lsa.py
nlpia/book/examples/ch05_2.ipynb
nlpia/book/examples/ch05_2.py
nlpia/book/examples/ch05_book_sentence_lsa.py
nlpia/book/examples/ch05_regression_digression.py
nlpia-0.5.2.dist-info/AUTHORS
nlpia-0.5.2.dist-info/AUTHORS.rst
nlpia-0.5.2.dist-info/LICENSE.txt
nlpia-0.5.2.dist-info/METADATA
nlpia-0.5.2.dist-info/WHEEL
nlpia-0.5.2.dist-info/top_level.txt
nlpia-0.5.2.dist-info/RECORD
